confluent/__init__.py
confluent/__main__.py
confluent/base/__init__.py
confluent/base/config.py
confluent/base/config_file_info.py
confluent/base/config_language_mapping.py
confluent/base/configuration_base.py
confluent/base/distributor_base.py
confluent/base/generator_base.py
confluent/base/generator_configuration.py
confluent/base/generator_naming_conventions.py
confluent/base/info.py
confluent/base/language_config_base.py
confluent/base/language_config_configuration.py
confluent/base/language_config_naming_conventions.py
confluent/base/language_type.py
confluent/base/name_converter.py
confluent/base/orchestrator.py
confluent/base/property.py
confluent/base/property_type.py
confluent/distributors/__init__.py
confluent/distributors/git_distributor.py
confluent/generators/__init__.py
confluent/generators/c_generator.py
confluent/generators/go_generator.py
confluent/generators/java_generator.py
confluent/generators/javascript_generator.py
confluent/generators/python_generator.py
confluent/generators/typescript_generator.py
confluent/helpers/__init__.py
confluent/helpers/package_handling.py
confluent/helpers/shell.py
confluent/language_configs/__init__.py
confluent/language_configs/c_config.py
confluent/language_configs/go_config.py
confluent/language_configs/java_config.py
confluent/language_configs/javascript_config.py
confluent/language_configs/python_config.py
confluent/language_configs/typescript_config.py
confluent-0.3.1.dist-info/LICENSE
confluent-0.3.1.dist-info/METADATA
confluent-0.3.1.dist-info/WHEEL
confluent-0.3.1.dist-info/entry_points.txt
confluent-0.3.1.dist-info/top_level.txt
confluent-0.3.1.dist-info/RECORD
