Metadata-Version: 2.1
Name: confluent
Version: 0.3.1
Summary: confluent keeps your language specific configs in sync
Home-page: https://github.com/monstermichl/confluent.git
Author: monstermichl
Keywords: multi,distributed,configuration,generator,confluent,languages,distribution,java,javascript,typescript,python,c,go
Classifier: Programming Language :: Python :: 3
Classifier: License :: OSI Approved :: MIT License
Classifier: Operating System :: OS Independent
Requires-Python: >=3.10
License-File: LICENSE
Requires-Dist: pyyaml >=6.0.1
Requires-Dist: schema >=0.7.5
Provides-Extra: dev
Requires-Dist: wheel >=0.41.1 ; extra == 'dev'
Requires-Dist: twine >=4.0.2 ; extra == 'dev'
Requires-Dist: ruff >=0.0.47 ; extra == 'dev'
Requires-Dist: coverage >=7.2.7 ; extra == 'dev'
